oy/__init__.py
oy/_prepare_app.py
oy/babel.py
oy/dynamicform.py
oy/exceptions.py
oy/globals.py
oy/helpers.py
oy/signals.py
oy/views.py
oy/wrappers.py
oy/boot/__init__.py
oy/boot/babel.py
oy/boot/boot_config.py
oy/boot/security.py
oy/boot/shell.py
oy/boot/sqla.py
oy/boot/flask_security_forms/__init__.py
oy/boot/flask_security_forms/change_password.py
oy/boot/flask_security_forms/login.py
oy/boot/flask_security_forms/recover.py
oy/boot/flask_security_forms/register.py
oy/cli/__init__.py
oy/cli/_vcs.py
oy/cli/database.py
oy/cli/oyinit.py
oy/cli/user.py
oy/contrib/__init__.py
oy/contrib/extbase.py
oy/contrib/admin/__init__.py
oy/contrib/admin/displayable_admin.py
oy/contrib/admin/page_admin.py
oy/contrib/admin/settings_admin.py
oy/contrib/admin/wrappers.py
oy/contrib/admin/fields/__init__.py
oy/contrib/admin/fields/bs3.py
oy/contrib/admin/fields/ckeditor.py
oy/contrib/admin/fields/tags.py
oy/contrib/admin/static/css/oyadmin.css
oy/contrib/admin/static/css/oyadmin.min.css
oy/contrib/admin/static/js/page-admin.js
oy/contrib/admin/static/js/page-admin.min.js
oy/contrib/admin/static/js/fields/ckeditor-setup.js
oy/contrib/admin/static/js/fields/ckeditor-setup.min.js
oy/contrib/admin/static/js/fields/file_input.js
oy/contrib/admin/static/js/fields/file_input.min.js
oy/contrib/admin/static/vendor/admin-lte/AdminLTE-without-plugins.css
oy/contrib/admin/static/vendor/admin-lte/AdminLTE-without-plugins.min.css
oy/contrib/admin/static/vendor/admin-lte/adminlte.js
oy/contrib/admin/static/vendor/admin-lte/adminlte.min.js
oy/contrib/admin/static/vendor/admin-lte/skin-black.css
oy/contrib/admin/static/vendor/admin-lte/skin-black.min.css
oy/contrib/admin/static/vendor/bootstrap/css/bootstrap.css
oy/contrib/admin/static/vendor/bootstrap/css/bootstrap.min.css
oy/contrib/admin/static/vendor/bootstrap/fonts/glyphicons-halflings-regular.eot
oy/contrib/admin/static/vendor/bootstrap/fonts/glyphicons-halflings-regular.svg
oy-0.1.7.dist-info/LICENSE
oy-0.1.7.dist-info/METADATA
oy-0.1.7.dist-info/WHEEL
oy-0.1.7.dist-info/entry_points.txt
oy-0.1.7.dist-info/top_level.txt
oy-0.1.7.dist-info/RECORD
