Metadata-Version: 2.1
Name: oy
Version: 0.1.7
Summary: A lightweight, modular, and extensible content management system based on Flask.
Home-page: https://github.com/mush42/oy-cms
Author: Musharraf Omer
Author-email: ibnomer2011@hotmail.com
License: MIT
Platform: any
Classifier: Development Status :: 4 - Beta
Classifier: Environment :: Web Environment
Classifier: Intended Audience :: Developers
Classifier: License :: OSI Approved :: MIT License
Classifier: Operating System :: OS Independent
Classifier: Programming Language :: Python
Classifier: Programming Language :: Python :: 3
Classifier: Programming Language :: Python :: 3.7
Classifier: Topic :: Internet :: WWW/HTTP :: Dynamic Content
Classifier: Topic :: Software Development :: Libraries :: Python Modules
Requires-Dist: bcrypt (==3.1.6)
Requires-Dist: filedepot (==0.6.0)
Requires-Dist: Flask (==1.0.2)
Requires-Dist: Flask-BabelEx (==0.9.3)
Requires-Dist: Flask-Cors (==3.0.7)
Requires-Dist: flask-marshmallow (==0.9.0)
Requires-Dist: Flask-Migrate (==2.3.1)
Requires-Dist: Flask-Security (==3.0.0)
Requires-Dist: Flask-SQLAlchemy (==2.3.2)
Requires-Dist: Flask-WTF (==0.14.2)
Requires-Dist: fleep (==1.0.1)
Requires-Dist: marshmallow-sqlalchemy (==0.15.0)
Requires-Dist: marshmallow (==2.18.0)
Requires-Dist: oy-libs-Flask-Admin (==1.5.3)
Requires-Dist: oy-libs-sqlalchemy-mptt (==0.2.4)
Requires-Dist: passlib (==1.7.1)
Requires-Dist: Pillow (==5.4.1)
Requires-Dist: python-dotenv (==0.10.1)
Requires-Dist: speaklater (==1.3)
Requires-Dist: SQLAlchemy (==1.2.17)
Requires-Dist: SQLAlchemy-Continuum (==1.3.7)
Requires-Dist: SQLAlchemy-Utils (==0.33.11)
Requires-Dist: unicode-slugify (==0.1.3)
Requires-Dist: validators (==0.12.4)
Requires-Dist: WTForms-Components (==0.10.3)
